{
    "name": "Fancode Live Matches Data in Json",
    "telegram": "https://t.me/+rQTz5VL8CRpjNTZl",
    "last update time": "01:28:29 PM 06-02-2025",
    "matches": [
        {
            "event_category": "Cricket",
            "title": "Sri Lanka vs Australia (Australia tour of Sri Lanka, 2025)",
            "src": "https://www.fancode.com/skillup-uploads/cms-media/Australia-Tour-of-Sri-Lanka_Old_1738055651553.jpg",
            "team_1": "Sri Lanka",
            "team_2": "Australia",
            "status": "LIVE",
            "event_name": "Australia tour of Sri Lanka, 2025",
            "match_name": "Sri Lanka vs Australia",
            "match_id": 115616,
            "startTime": "10:00:00 AM 06-02-2025",
            "dai_url": "https://sonypartnersdaimenew.akamaized.net/hls/live/2094588/AUSVSSL/master.m3u8?No 'dashUrl' found in the response.",
            "adfree_url": "https://sonypartnersdaimenew.akamaized.net/hls/live/2094588/AUSVSSL/master.m3u8?No 'dashUrl' found in the response."
        },
        {
            "event_category": "Cricket",
            "title": "Ireland vs Zimbabwe (Ireland tour of Zimbabwe, 2025)",
            "src": "https://www.fancode.com/skillup-uploads/cms-media/Ireland-Tour-of-Zimbabwe-Test_OLD_1738767396284.jpg",
            "team_1": "Ireland",
            "team_2": "Zimbabwe",
            "status": "LIVE",
            "event_name": "Ireland tour of Zimbabwe, 2025",
            "match_name": "Ireland vs Zimbabwe",
            "match_id": 116935,
            "startTime": "01:30:00 PM 06-02-2025",
            "dai_url": "https://dai.google.com/linear/hls/event/1fNCotbvT4-xpT71DmtyWg/master.m3u8",
            "adfree_url": "https://dai.fancode.com/primary/116935_english_hls_6774ta-no/index.m3u8"
        },
        {
            "event_category": "Cricket",
            "title": "Thailand Women vs Netherlands Women (Nepal Women's T20I Triangular Series)",
            "src": "https://www.fancode.com/skillup-uploads/cms-media/Nepal-Women's-T20I-Triangular-Series-old-match-8.png",
            "team_1": "Thailand Women",
            "team_2": "Netherlands Women",
            "status": "LIVE",
            "event_name": "Nepal Women's T20I Triangular Series",
            "match_name": "Thailand Women vs Netherlands Women",
            "match_id": 117643,
            "startTime": "12:00:00 PM 06-02-2025",
            "dai_url": "https://dai.google.com/linear/hls/event/QZyCRkzDS9CozYmZMXDuDQ/master.m3u8",
            "adfree_url": "https://dai.fancode.com/primary/117643_english_hls_6357ta-di/index.m3u8"
        },
        {
            "event_category": "Cricket",
            "title": "Chhattisgarh Warriors vs Delhi Royals (Legend 90, 2025)",
            "src": "https://www.fancode.com/skillup-uploads/cms-media/118225_4824_CW_DLR_fc-Web.jpg",
            "team_1": "Chhattisgarh Warriors",
            "team_2": "Delhi Royals",
            "status": "UPCOMING",
            "event_name": "Legend 90, 2025",
            "match_name": "Chhattisgarh Warriors vs Delhi Royals",
            "match_id": 118225,
            "startTime": "07:00:00 PM 06-02-2025"
        },
        {
            "event_category": "Cricket",
            "title": "MI Emirates vs Sharjah Warriorz (DP World International League T20, 2025)",
            "src": "https://www.fancode.com/skillup-uploads/cms-media/115979_4730_MIE_SWR_fc-web.jpg",
            "team_1": "MI Emirates",
            "team_2": "Sharjah Warriorz",
            "status": "UPCOMING",
            "event_name": "DP World International League T20, 2025",
            "match_name": "MI Emirates vs Sharjah Warriorz",
            "match_id": 115983,
            "startTime": "08:00:00 PM 06-02-2025"
        },
        {
            "event_category": "Cricket",
            "title": "Malta vs Austria (ECI Malta, 2025)",
            "src": "https://www.fancode.com/skillup-uploads/cms-media/117817_4805_MAL_AUT_fc-Web.jpg",
            "team_1": "Malta",
            "team_2": "Austria",
            "status": "UPCOMING",
            "event_name": "ECI Malta, 2025",
            "match_name": "Malta vs Austria",
            "match_id": 117817,
            "startTime": "01:45:00 PM 06-02-2025"
        },
        {
            "event_category": "Cricket",
            "title": "New Star Club vs Sath Gaon Club (Guwahati Premier League, 2025)",
            "src": "https://www.fancode.com/skillup-uploads/cms-media/117449_4781_NSC_SGC_fc-web.jpg",
            "team_1": "New Star Club",
            "team_2": "Sath Gaon Club",
            "status": "UPCOMING",
            "event_name": "Guwahati Premier League, 2025",
            "match_name": "New Star Club vs Sath Gaon Club",
            "match_id": 117449,
            "startTime": "03:00:00 PM 06-02-2025"
        },
        {
            "event_category": "Cricket",
            "title": "Malta vs Hungary (ECI Malta, 2025)",
            "src": "https://www.fancode.com/skillup-uploads/cms-media/117818_4805_MAL_HUN_fc-Web.jpg",
            "team_1": "Malta",
            "team_2": "Hungary",
            "status": "UPCOMING",
            "event_name": "ECI Malta, 2025",
            "match_name": "Malta vs Hungary",
            "match_id": 117818,
            "startTime": "03:45:00 PM 06-02-2025"
        },
        {
            "event_category": "Cricket",
            "title": "Hungary vs Austria (ECI Malta, 2025)",
            "src": "https://www.fancode.com/skillup-uploads/cms-media/117819_4805_HUN_AUT_fc-Web.jpg",
            "team_1": "Hungary",
            "team_2": "Austria",
            "status": "UPCOMING",
            "event_name": "ECI Malta, 2025",
            "match_name": "Hungary vs Austria",
            "match_id": 117819,
            "startTime": "05:45:00 PM 06-02-2025"
        },
        {
            "event_category": "Cricket",
            "title": "Malta vs Austria (ECI Malta, 2025)",
            "src": "https://www.fancode.com/skillup-uploads/cms-media/117820_4805_MAL_AUT_fc-Web.jpg",
            "team_1": "Malta",
            "team_2": "Austria",
            "status": "UPCOMING",
            "event_name": "ECI Malta, 2025",
            "match_name": "Malta vs Austria",
            "match_id": 117820,
            "startTime": "07:45:00 PM 06-02-2025"
        },
        {
            "event_category": "Cricket",
            "title": "Giflo Young Peoples CC vs Worcester United (Boland T20 Super League Finals, 2025)",
            "src": "https://www.fancode.com/skillup-uploads/cms-media/117492_4787_YPS_WUT_Fc-Web.jpg",
            "team_1": "Giflo Young Peoples CC",
            "team_2": "Worcester United",
            "status": "UPCOMING",
            "event_name": "Boland T20 Super League Finals, 2025",
            "match_name": "Giflo Young Peoples CC vs Worcester United",
            "match_id": 117492,
            "startTime": "10:00:00 PM 06-02-2025"
        },
        {
            "event_category": "Cricket",
            "title": "Coimbra Knights vs Malo (ECSN Portugal, 2025)",
            "src": "https://www.fancode.com/skillup-uploads/cms-media/117763_4800_CK_MAL_fc-web.jpg",
            "team_1": "Coimbra Knights",
            "team_2": "Malo",
            "status": "UPCOMING",
            "event_name": "ECSN Portugal, 2025",
            "match_name": "Coimbra Knights vs Malo",
            "match_id": 117763,
            "startTime": "11:30:00 PM 06-02-2025"
        }
    ]
}