{
    "name": "Fancode Live Matches Data in Json",
    "telegram": "https://t.me/+rQTz5VL8CRpjNTZl",
    "last update time": "11:53:58 PM 06-12-2025",
    "matches": [
        {
            "event_category": "Motorsports",
            "title": "Feature Race vs Yas Island (F2 ABU DHABI 2025)",
            "src": "https://www.fancode.com/skillup-uploads/cms-media/Formula2_Old_match-card-(1).jpg",
            "team_1": "Feature Race",
            "team_2": "Yas Island",
            "status": "UPCOMING",
            "event_name": "F2 ABU DHABI 2025",
            "match_name": "Feature Race",
            "match_id": 121615,
            "startTime": "02:45:00 PM 07-12-2025"
        },
        {
            "event_category": "Formula 1",
            "title": "Race vs Abu Dhabi (F1 ETIHAD AIRWAYS ABU DHABI GRAND PRIX 2025)",
            "src": "https://www.fancode.com/skillup-uploads/cms-media/F1-AbuDhabi_Old_match-card.jpg",
            "team_1": "Race",
            "team_2": "Abu Dhabi",
            "status": "UPCOMING",
            "event_name": "F1 ETIHAD AIRWAYS ABU DHABI GRAND PRIX 2025",
            "match_name": "Race",
            "match_id": 118500,
            "startTime": "06:30:00 PM 07-12-2025"
        },
        {
            "event_category": "Motorsports",
            "title": "F1 Kids vs Abu Dhabi (F1 Kids)",
            "src": "https://www.fancode.com/skillup-uploads/cms-media/Abu_Dhabi_GP_F1_Old_match-card.jpg",
            "team_1": "F1 Kids",
            "team_2": "Abu Dhabi",
            "status": "UPCOMING",
            "event_name": "F1 Kids",
            "match_name": "F1 Kids",
            "match_id": 138024,
            "startTime": "06:30:00 PM 07-12-2025"
        },
        {
            "event_category": "Horse Racing",
            "title": "Longines Hong Kong Cup 2025 vs Sha Tin Racecourse (Longines Hong Kong Cup 2025)",
            "src": "https://www.fancode.com/skillup-uploads/cms-media/Longines-Hong-Kong-Cup-2025_Old_match-card.jpg",
            "team_1": "Longines Hong Kong Cup 2025",
            "team_2": "Sha Tin Racecourse",
            "status": "UPCOMING",
            "event_name": "Longines Hong Kong Cup 2025",
            "match_name": "Longines Hong Kong Cup 2025",
            "match_id": 138690,
            "startTime": "01:00:00 PM 14-12-2025"
        },
        {
            "event_category": "Motorsports",
            "title": "Indian Supercross Racing League vs Calicut (Indian Supercross Racing League)",
            "src": "https://www.fancode.com/skillup-uploads/cms-media/ISRL_Old_match-card_2_1764661126526.jpg",
            "team_1": "Indian Supercross Racing League",
            "team_2": "Calicut",
            "status": "UPCOMING",
            "event_name": "Indian Supercross Racing League",
            "match_name": "Indian Supercross Racing League",
            "match_id": 138663,
            "startTime": "07:00:00 PM 21-12-2025"
        }
    ]
}