{
    "name": "Fancode Live Matches Data in Json",
    "telegram": "https://t.me/+rQTz5VL8CRpjNTZl",
    "last update time": "03:04:43 PM 04-11-2024",
    "matches": [
        {
            "event_category": "Cricket",
            "title": "Gozo Zalmi vs MMA Titans (ECS Malta, 2024)",
            "src": "https://www.fancode.com/skillup-uploads/cms-media/ECS_Malta_-2024_Old_match-card_1_1729570461679.jpg",
            "team_1": "Gozo Zalmi",
            "team_2": "MMA Titans",
            "status": "LIVE",
            "event_name": "ECS Malta, 2024",
            "match_name": "Gozo Zalmi vs MMA Titans",
            "match_id": 111579,
            "startTime": "03:00:00 PM 04-11-2024",
            "dai_url": "https://dai.google.com/linear/hls/event/bU0B2ALjTeqFsjklUM1Pjg/master.m3u8",
            "adfree_url": "https://dai.fancode.com/primary/111579_english_hls_5426ta-no/index.m3u8"
        },
        {
            "event_category": "Football",
            "title": "Western United vs Melbourne City (A League 2024-25)",
            "src": "https://www.fancode.com/skillup-uploads/cms-media/110910_4567_WST_MLC_fc-web_1728983127544.jpg",
            "team_1": "Western United",
            "team_2": "Melbourne City",
            "status": "LIVE",
            "event_name": "A League 2024-25",
            "match_name": "Western United vs Melbourne City",
            "match_id": 110910,
            "startTime": "01:30:00 PM 04-11-2024",
            "dai_url": "https://dai.google.com/linear/hls/event/ESxLZBNkRdGtSNtXqSIyHg/master.m3u8",
            "adfree_url": "https://dai.fancode.com/primary/110910_english_hls_5402ta-di/index.m3u8"
        },
        {
            "event_category": "Cricket",
            "title": "Marsa vs Royal Strikers (ECS Malta, 2024)",
            "src": "https://www.fancode.com/skillup-uploads/cms-media/ECS_Malta_-2024_Old_match-card_2_1729570461132.jpg",
            "team_1": "Marsa",
            "team_2": "Royal Strikers",
            "status": "UPCOMING",
            "event_name": "ECS Malta, 2024",
            "match_name": "Marsa vs Royal Strikers",
            "match_id": 111580,
            "startTime": "05:00:00 PM 04-11-2024"
        },
        {
            "event_category": "Cricket",
            "title": "Hurricanes vs Tusker CC (Qatar Pro League, 2024)",
            "src": "https://www.fancode.com/skillup-uploads/cms-media/111802_4593_HUR_TCC_fc-web.jpg",
            "team_1": "Hurricanes",
            "team_2": "Tusker CC",
            "status": "UPCOMING",
            "event_name": "Qatar Pro League, 2024",
            "match_name": "Hurricanes vs Tusker CC",
            "match_id": 111802,
            "startTime": "05:30:00 PM 04-11-2024"
        },
        {
            "event_category": "Cricket",
            "title": "Combined Campuses and Colleges vs West Indies Academy (CG United Super50 Cup, 2024)",
            "src": "https://www.fancode.com/skillup-uploads/cms-media/112015_4596_CCC_WIC_fc-web.jpg",
            "team_1": "Combined Campuses and Colleges",
            "team_2": "West Indies Academy",
            "status": "UPCOMING",
            "event_name": "CG United Super50 Cup, 2024",
            "match_name": "Combined Campuses and Colleges vs West Indies Academy",
            "match_id": 112015,
            "startTime": "06:30:00 PM 04-11-2024"
        },
        {
            "event_category": "Cricket",
            "title": "Sharjah vs Abu Dhabi (Emirates D20, 2024)",
            "src": "https://www.fancode.com/skillup-uploads/cms-media/111684_4589_SHA_ABD_fc-web.jpg",
            "team_1": "Sharjah",
            "team_2": "Abu Dhabi",
            "status": "UPCOMING",
            "event_name": "Emirates D20, 2024",
            "match_name": "Sharjah vs Abu Dhabi",
            "match_id": 111684,
            "startTime": "07:00:00 PM 04-11-2024"
        },
        {
            "event_category": "Cricket",
            "title": "Royal Strikers vs MMA Titans (ECS Malta, 2024)",
            "src": "https://www.fancode.com/skillup-uploads/cms-media/ECS_Malta_-2024_Old_match-card_3_1729570461562.jpg",
            "team_1": "Royal Strikers",
            "team_2": "MMA Titans",
            "status": "UPCOMING",
            "event_name": "ECS Malta, 2024",
            "match_name": "Royal Strikers vs MMA Titans",
            "match_id": 111581,
            "startTime": "07:15:00 PM 04-11-2024"
        },
        {
            "event_category": "Cricket",
            "title": "Asian CC vs CBCC (Qatar Pro League, 2024)",
            "src": "https://www.fancode.com/skillup-uploads/cms-media/111803_4593_ACC_CBC_fc-web.jpg",
            "team_1": "Asian CC",
            "team_2": "CBCC",
            "status": "UPCOMING",
            "event_name": "Qatar Pro League, 2024",
            "match_name": "Asian CC vs CBCC",
            "match_id": 111803,
            "startTime": "09:30:00 PM 04-11-2024"
        },
        {
            "event_category": "Cricket",
            "title": "NCM Investment vs Al Hajery Team XI (KCC T20 Elite Cup, 2024)",
            "src": "https://www.fancode.com/skillup-uploads/cms-media/KCC-T20-Elite-Cup-3rd-Edition_old_01.jpg",
            "team_1": "NCM Investment",
            "team_2": "Al Hajery Team XI",
            "status": "UPCOMING",
            "event_name": "KCC T20 Elite Cup, 2024",
            "match_name": "NCM Investment vs Al Hajery Team XI",
            "match_id": 110515,
            "startTime": "10:30:00 PM 04-11-2024"
        },
        {
            "event_category": "Cricket",
            "title": "Ajman vs Fujairah (Emirates D20, 2024)",
            "src": "https://www.fancode.com/skillup-uploads/cms-media/111685_4589_AJM_FUJ_fc-web.jpg",
            "team_1": "Ajman",
            "team_2": "Fujairah",
            "status": "UPCOMING",
            "event_name": "Emirates D20, 2024",
            "match_name": "Ajman vs Fujairah",
            "match_id": 111685,
            "startTime": "11:00:00 PM 04-11-2024"
        },
        {
            "event_category": "Football",
            "title": "Al Wasl vs Al Sadd (AFC Champions League Elite 2024-25)",
            "src": "https://fancode.com/skillup-uploads/prod-images/2024/09/108663_4475_AWL_SDD_fc-web.jpg",
            "team_1": "Al Wasl",
            "team_2": "Al Sadd",
            "status": "UPCOMING",
            "event_name": "AFC Champions League Elite 2024-25",
            "match_name": "Al Wasl vs Al Sadd",
            "match_id": 108663,
            "startTime": "07:30:00 PM 04-11-2024"
        },
        {
            "event_category": "Football",
            "title": "Persepolis FC vs Al Gharafa (AFC Champions League Elite 2024-25)",
            "src": "https://fancode.com/skillup-uploads/prod-images/2024/09/108665_4475_PPL_AGH_fc-web.jpg",
            "team_1": "Persepolis FC",
            "team_2": "Al Gharafa",
            "status": "UPCOMING",
            "event_name": "AFC Champions League Elite 2024-25",
            "match_name": "Persepolis FC vs Al Gharafa",
            "match_id": 108665,
            "startTime": "09:30:00 PM 04-11-2024"
        }
    ]
}