{
    "name": "Fancode Live Matches Data in Json",
    "telegram": "https://t.me/+rQTz5VL8CRpjNTZl",
    "last update time": "07:38:11 AM 16-06-2025",
    "matches": [
        {
            "event_category": "Cricket",
            "title": "Cambodia vs Indonesia (Cambodia tour of Indonesia, 2025)",
            "src": "https://www.fancode.com/skillup-uploads/cms-media/Cambodia-tour-of-Indonesia-old.jpg",
            "team_1": "Cambodia",
            "team_2": "Indonesia",
            "status": "LIVE",
            "event_name": "Cambodia tour of Indonesia, 2025",
            "match_name": "Cambodia vs Indonesia",
            "match_id": 129123,
            "startTime": "07:00:00 AM 16-06-2025",
            "dai_url": "https://dai.google.com/linear/hls/event/ptQ3vIJ6S1WPNCg5BgHv5w/master.m3u8",
            "adfree_url": "https://dai.fancode.com/primary/129123_english_hls_25003ta-di_h264/index.m3u8"
        },
        {
            "event_category": "Cricket",
            "title": "Lux Shyam Kolkata Tigers vs Servotech Siliguri Strikers (Bengal Pro T20 league, 2025)",
            "src": "https://www.fancode.com/skillup-uploads/cms-media/128059_5282_LSKT_SSS_fc-Web.jpg",
            "team_1": "Lux Shyam Kolkata Tigers",
            "team_2": "Servotech Siliguri Strikers",
            "status": "UPCOMING",
            "event_name": "Bengal Pro T20 league, 2025",
            "match_name": "Lux Shyam Kolkata Tigers vs Servotech Siliguri Strikers",
            "match_id": 128059,
            "startTime": "01:00:00 PM 16-06-2025"
        },
        {
            "event_category": "Cricket",
            "title": "JMD Kutch Riders vs Anmol Kings Halar (Saurashtra Pro T20 League, 2025)",
            "src": "https://www.fancode.com/skillup-uploads/cms-media/128195_5287_HH_KW_fc-Web.jpg",
            "team_1": "JMD Kutch Riders",
            "team_2": "Anmol Kings Halar",
            "status": "UPCOMING",
            "event_name": "Saurashtra Pro T20 League, 2025",
            "match_name": "JMD Kutch Riders vs Anmol Kings Halar",
            "match_id": 129187,
            "startTime": "03:00:00 PM 16-06-2025"
        },
        {
            "event_category": "Cricket",
            "title": "Sri Lanka Emerging vs West Indies Academy (Sri Lanka Emerging tour of West Indies)",
            "src": "https://www.fancode.com/skillup-uploads/cms-media/Sri-Lanka-Emerging-tour-of-West-Indies-old-match-card.png",
            "team_1": "Sri Lanka Emerging",
            "team_2": "West Indies Academy",
            "status": "PAUSED",
            "event_name": "Sri Lanka Emerging tour of West Indies",
            "match_name": "Sri Lanka Emerging vs West Indies Academy",
            "match_id": 128403,
            "startTime": "07:30:00 PM 14-06-2025"
        },
        {
            "event_category": "Cricket",
            "title": "Rashmi Medinipur Wizards vs Adamas Howrah Warriors (Bengal Pro T20 league, 2025)",
            "src": "https://www.fancode.com/skillup-uploads/cms-media/128060_5282_RMW_AHW_fc-Web.jpg",
            "team_1": "Rashmi Medinipur Wizards",
            "team_2": "Adamas Howrah Warriors",
            "status": "UPCOMING",
            "event_name": "Bengal Pro T20 league, 2025",
            "match_name": "Rashmi Medinipur Wizards vs Adamas Howrah Warriors",
            "match_id": 128060,
            "startTime": "07:00:00 PM 16-06-2025"
        },
        {
            "event_category": "Cricket",
            "title": "Dindigul Dragons vs Chepauk Super Gillies (Shriram Capital TNPL)",
            "src": "https://www.fancode.com/skillup-uploads/cms-media/TNPL_Dindigul_v_Chepauk_Old_match_card.jpg",
            "team_1": "Dindigul Dragons",
            "team_2": "Chepauk Super Gillies",
            "status": "UPCOMING",
            "event_name": "Shriram Capital TNPL",
            "match_name": "Dindigul Dragons vs Chepauk Super Gillies",
            "match_id": 126541,
            "startTime": "07:15:00 PM 16-06-2025"
        },
        {
            "event_category": "Cricket",
            "title": "Nepal vs Netherlands (Nepal and Netherlands tour of Scotland, 2025)",
            "src": "https://www.fancode.com/skillup-uploads/cms-media/127627_5263_NEP_NED_fc-Web.png",
            "team_1": "Nepal",
            "team_2": "Netherlands",
            "status": "UPCOMING",
            "event_name": "Nepal and Netherlands tour of Scotland, 2025",
            "match_name": "Nepal vs Netherlands",
            "match_id": 127627,
            "startTime": "07:30:00 PM 16-06-2025"
        },
        {
            "event_category": "Cricket",
            "title": "Aryan Sorath Lions vs Dita Gohilwad Titans (Saurashtra Pro T20 League, 2025)",
            "src": "https://www.fancode.com/skillup-uploads/cms-media/128198_5287_SL_GG_fc-Web.jpg",
            "team_1": "Aryan Sorath Lions",
            "team_2": "Dita Gohilwad Titans",
            "status": "UPCOMING",
            "event_name": "Saurashtra Pro T20 League, 2025",
            "match_name": "Aryan Sorath Lions vs Dita Gohilwad Titans",
            "match_id": 128198,
            "startTime": "07:30:00 PM 16-06-2025"
        },
        {
            "event_category": "Cricket",
            "title": "Alpine Sporting Club vs Cricket Association Of Tathangchen (Sikkim T20 League, 2025)",
            "src": "https://www.fancode.com/skillup-uploads/cms-media/128709_5312_ASC_CAT_fc-web.jpg",
            "team_1": "Alpine Sporting Club",
            "team_2": "Cricket Association Of Tathangchen",
            "status": "UPCOMING",
            "event_name": "Sikkim T20 League, 2025",
            "match_name": "Alpine Sporting Club vs Cricket Association Of Tathangchen",
            "match_id": 128709,
            "startTime": "08:30:00 AM 16-06-2025"
        },
        {
            "event_category": "Cricket",
            "title": "Lux Shyam Kolkata Tigers Womens vs Sobisco Smashers Malda Womens (Bengal Women's Pro T20 League, 2025)",
            "src": "https://www.fancode.com/skillup-uploads/cms-media/128089_5283_LSKT-W_SSM-W_fc-Web.jpg",
            "team_1": "Lux Shyam Kolkata Tigers Womens",
            "team_2": "Sobisco Smashers Malda Womens",
            "status": "UPCOMING",
            "event_name": "Bengal Women's Pro T20 League, 2025",
            "match_name": "Lux Shyam Kolkata Tigers Womens vs Sobisco Smashers Malda Womens",
            "match_id": 128089,
            "startTime": "09:00:00 AM 16-06-2025"
        },
        {
            "event_category": "Cricket",
            "title": "Prague Spartans vs Praha Dominators (ECS Czechia, 2025)",
            "src": "https://images.fancode.com/aig/match/v1/129028_CASACARDS_APP.png",
            "team_1": "Prague Spartans",
            "team_2": "Praha Dominators",
            "status": "UPCOMING",
            "event_name": "ECS Czechia, 2025",
            "match_name": "Prague Spartans vs Praha Dominators",
            "match_id": 129028,
            "startTime": "12:15:00 PM 16-06-2025"
        },
        {
            "event_category": "Cricket",
            "title": "Yuksom Capitals vs Avengers C.C (Sikkim T20 League, 2025)",
            "src": "https://www.fancode.com/skillup-uploads/cms-media/128710_5312_YC_ACC_fc-web.jpg",
            "team_1": "Yuksom Capitals",
            "team_2": "Avengers C.C",
            "status": "UPCOMING",
            "event_name": "Sikkim T20 League, 2025",
            "match_name": "Yuksom Capitals vs Avengers C.C",
            "match_id": 128710,
            "startTime": "12:30:00 PM 16-06-2025"
        },
        {
            "event_category": "Cricket",
            "title": "Murshidabad Kueens Womens vs Shrachi Rarh Tigers Womens (Bengal Women's Pro T20 League, 2025)",
            "src": "https://www.fancode.com/skillup-uploads/cms-media/128090_5283_MK-W_SRT-W_fc-Web.jpg",
            "team_1": "Murshidabad Kueens Womens",
            "team_2": "Shrachi Rarh Tigers Womens",
            "status": "UPCOMING",
            "event_name": "Bengal Women's Pro T20 League, 2025",
            "match_name": "Murshidabad Kueens Womens vs Shrachi Rarh Tigers Womens",
            "match_id": 128090,
            "startTime": "01:30:00 PM 16-06-2025"
        },
        {
            "event_category": "Cricket",
            "title": "Prague Spartans vs Vinohrady (ECS Czechia, 2025)",
            "src": "https://images.fancode.com/aig/match/v1/129029_CASACARDS_APP.png",
            "team_1": "Prague Spartans",
            "team_2": "Vinohrady",
            "status": "UPCOMING",
            "event_name": "ECS Czechia, 2025",
            "match_name": "Prague Spartans vs Vinohrady",
            "match_id": 129029,
            "startTime": "02:15:00 PM 16-06-2025"
        },
        {
            "event_category": "Cricket",
            "title": "Alembic Warriors vs Pruthvi Panthers (Baroda Premier League, 2025)",
            "src": "https://www.fancode.com/skillup-uploads/cms-media/128672_5310_AWS_PTP_fc-Web.jpg",
            "team_1": "Alembic Warriors",
            "team_2": "Pruthvi Panthers",
            "status": "UPCOMING",
            "event_name": "Baroda Premier League, 2025",
            "match_name": "Alembic Warriors vs Pruthvi Panthers",
            "match_id": 128672,
            "startTime": "02:45:00 PM 16-06-2025"
        },
        {
            "event_category": "Cricket",
            "title": "Chambal Ghariyals vs Rewa Jaguars (Madhya Pradesh League, 2025)",
            "src": "https://www.fancode.com/skillup-uploads/cms-media/128441_5300_CGS_RW_fc-web.jpg",
            "team_1": "Chambal Ghariyals",
            "team_2": "Rewa Jaguars",
            "status": "UPCOMING",
            "event_name": "Madhya Pradesh League, 2025",
            "match_name": "Chambal Ghariyals vs Rewa Jaguars",
            "match_id": 128441,
            "startTime": "03:00:00 PM 16-06-2025"
        },
        {
            "event_category": "Cricket",
            "title": "Praha Dominators vs Moravian (ECS Czechia, 2025)",
            "src": "https://images.fancode.com/aig/match/v1/129030_CASACARDS_APP.png",
            "team_1": "Praha Dominators",
            "team_2": "Moravian",
            "status": "UPCOMING",
            "event_name": "ECS Czechia, 2025",
            "match_name": "Praha Dominators vs Moravian",
            "match_id": 129030,
            "startTime": "04:15:00 PM 16-06-2025"
        },
        {
            "event_category": "Cricket",
            "title": "Vinohrady vs Ostrava (ECS Czechia, 2025)",
            "src": "https://images.fancode.com/aig/match/v1/129031_CASACARDS_APP.png",
            "team_1": "Vinohrady",
            "team_2": "Ostrava",
            "status": "UPCOMING",
            "event_name": "ECS Czechia, 2025",
            "match_name": "Vinohrady vs Ostrava",
            "match_id": 129031,
            "startTime": "06:15:00 PM 16-06-2025"
        },
        {
            "event_category": "Cricket",
            "title": "Ami Super Avengers vs A4 Power Strikers (Baroda Premier League, 2025)",
            "src": "https://www.fancode.com/skillup-uploads/cms-media/128673_5310_ASV_APT_fc-Web.jpg",
            "team_1": "Ami Super Avengers",
            "team_2": "A4 Power Strikers",
            "status": "UPCOMING",
            "event_name": "Baroda Premier League, 2025",
            "match_name": "Ami Super Avengers vs A4 Power Strikers",
            "match_id": 128673,
            "startTime": "06:45:00 PM 16-06-2025"
        },
        {
            "event_category": "Cricket",
            "title": "Gwalior Cheetahs vs Jabalpur Royal Lions (Madhya Pradesh League, 2025)",
            "src": "https://www.fancode.com/skillup-uploads/cms-media/128442_5300_GC_JRL_fc-web.jpg",
            "team_1": "Gwalior Cheetahs",
            "team_2": "Jabalpur Royal Lions",
            "status": "UPCOMING",
            "event_name": "Madhya Pradesh League, 2025",
            "match_name": "Gwalior Cheetahs vs Jabalpur Royal Lions",
            "match_id": 128442,
            "startTime": "07:30:00 PM 16-06-2025"
        },
        {
            "event_category": "Cricket",
            "title": "Canada vs Cayman Islands (ICC Men's T20 World Cup Americas Regional Final)",
            "src": "https://www.fancode.com/skillup-uploads/cms-media/128697_5311_CAN_CAY_fc-web.jpg",
            "team_1": "Canada",
            "team_2": "Cayman Islands",
            "status": "UPCOMING",
            "event_name": "ICC Men's T20 World Cup Americas Regional Final",
            "match_name": "Canada vs Cayman Islands",
            "match_id": 128697,
            "startTime": "08:00:00 PM 16-06-2025"
        },
        {
            "event_category": "Cricket",
            "title": "Ostrava vs Moravian (ECS Czechia, 2025)",
            "src": "https://images.fancode.com/aig/match/v1/129032_CASACARDS_APP.png",
            "team_1": "Ostrava",
            "team_2": "Moravian",
            "status": "UPCOMING",
            "event_name": "ECS Czechia, 2025",
            "match_name": "Ostrava vs Moravian",
            "match_id": 129032,
            "startTime": "08:30:00 PM 16-06-2025"
        },
        {
            "event_category": "Cricket",
            "title": "Chicago Steelpan Players vs Soca Kings (Dream11 Trinidad T10 Blast, 7th Edition, 2025)",
            "src": "https://www.fancode.com/skillup-uploads/cms-media/128219_5288_SPK_SCK_fc-Web.jpg",
            "team_1": "Chicago Steelpan Players",
            "team_2": "Soca Kings",
            "status": "UPCOMING",
            "event_name": "Dream11 Trinidad T10 Blast, 7th Edition, 2025",
            "match_name": "Chicago Steelpan Players vs Soca Kings",
            "match_id": 128219,
            "startTime": "09:30:00 PM 16-06-2025"
        },
        {
            "event_category": "Cricket",
            "title": "ACE KRM Panthers vs SBS CC (KCC T20 Challengers A League, 3rd Edition, 2025)",
            "src": "https://images.fancode.com/aig/match/v2/125418_CASACARDS_APP.png",
            "team_1": "ACE KRM Panthers",
            "team_2": "SBS CC",
            "status": "UPCOMING",
            "event_name": "KCC T20 Challengers A League, 3rd Edition, 2025",
            "match_name": "ACE KRM Panthers vs SBS CC",
            "match_id": 125418,
            "startTime": "11:00:00 PM 16-06-2025"
        },
        {
            "event_category": "Cricket",
            "title": "Scarlet Ibis Scorchers vs Bess Motors Blue Devils (Dream11 Trinidad T10 Blast, 7th Edition, 2025)",
            "src": "https://www.fancode.com/skillup-uploads/cms-media/128220_5288_SLS_BLD_fc-Web.jpg",
            "team_1": "Scarlet Ibis Scorchers",
            "team_2": "Bess Motors Blue Devils",
            "status": "UPCOMING",
            "event_name": "Dream11 Trinidad T10 Blast, 7th Edition, 2025",
            "match_name": "Scarlet Ibis Scorchers vs Bess Motors Blue Devils",
            "match_id": 128220,
            "startTime": "12:00:00 AM 17-06-2025"
        },
        {
            "event_category": "Cricket",
            "title": "Bermuda vs Bahamas (ICC Men's T20 World Cup Americas Regional Final)",
            "src": "https://www.fancode.com/skillup-uploads/cms-media/128698_5311_BER_BAH_fc-web.jpg",
            "team_1": "Bermuda",
            "team_2": "Bahamas",
            "status": "UPCOMING",
            "event_name": "ICC Men's T20 World Cup Americas Regional Final",
            "match_name": "Bermuda vs Bahamas",
            "match_id": 128698,
            "startTime": "01:00:00 AM 17-06-2025"
        },
        {
            "event_category": "Cricket",
            "title": "Samp Army Cocrico Cavaliers vs Leatherback Strikers (Dream11 Trinidad T10 Blast, 7th Edition, 2025)",
            "src": "https://www.fancode.com/skillup-uploads/cms-media/128221_5288_SCL_TLS_fc-Web.jpg",
            "team_1": "Samp Army Cocrico Cavaliers",
            "team_2": "Leatherback Strikers",
            "status": "UPCOMING",
            "event_name": "Dream11 Trinidad T10 Blast, 7th Edition, 2025",
            "match_name": "Samp Army Cocrico Cavaliers vs Leatherback Strikers",
            "match_id": 128221,
            "startTime": "02:30:00 AM 17-06-2025"
        },
        {
            "event_category": "Cricket",
            "title": "Sri Lanka vs Bangladesh (Bangladesh tour of Sri Lanka, 2025)",
            "src": "https://www.fancode.com/skillup-uploads/cms-media/Bangladesh-tour-of-Sri-Lanka-2025-old-match-card.png",
            "team_1": "Sri Lanka",
            "team_2": "Bangladesh",
            "status": "UPCOMING",
            "event_name": "Bangladesh tour of Sri Lanka, 2025",
            "match_name": "Sri Lanka vs Bangladesh",
            "match_id": 128426,
            "startTime": "10:00:00 AM 17-06-2025"
        },
        {
            "event_category": "Cricket",
            "title": "Pakyong XI vs Irises C.C (Sikkim T20 League, 2025)",
            "src": "https://www.fancode.com/skillup-uploads/cms-media/128711_5312_PAK_ICC_fc-web.jpg",
            "team_1": "Pakyong XI",
            "team_2": "Irises C.C",
            "status": "UPCOMING",
            "event_name": "Sikkim T20 League, 2025",
            "match_name": "Pakyong XI vs Irises C.C",
            "match_id": 128711,
            "startTime": "08:30:00 AM 17-06-2025"
        },
        {
            "event_category": "Cricket",
            "title": "Servotech Siliguri Strikers Womens vs Rashmi Medinipur Wizards Womens (Bengal Women's Pro T20 League, 2025)",
            "src": "https://www.fancode.com/skillup-uploads/cms-media/128091_5283_SSS-W_RMW-W_fc-Web.jpg",
            "team_1": "Servotech Siliguri Strikers Womens",
            "team_2": "Rashmi Medinipur Wizards Womens",
            "status": "UPCOMING",
            "event_name": "Bengal Women's Pro T20 League, 2025",
            "match_name": "Servotech Siliguri Strikers Womens vs Rashmi Medinipur Wizards Womens",
            "match_id": 128091,
            "startTime": "09:00:00 AM 17-06-2025"
        },
        {
            "event_category": "Cricket",
            "title": "Sobisco Smashers Malda vs Servotech Siliguri Strikers (Bengal Pro T20 league, 2025)",
            "src": "https://www.fancode.com/skillup-uploads/cms-media/128061_5282_SSM_SSS_fc-Web.jpg",
            "team_1": "Sobisco Smashers Malda",
            "team_2": "Servotech Siliguri Strikers",
            "status": "UPCOMING",
            "event_name": "Bengal Pro T20 league, 2025",
            "match_name": "Sobisco Smashers Malda vs Servotech Siliguri Strikers",
            "match_id": 128061,
            "startTime": "01:00:00 PM 17-06-2025"
        }
    ]
}