{
    "name": "Fancode Live Matches Data in Json",
    "telegram": "https://t.me/+rQTz5VL8CRpjNTZl",
    "last update time": "03:54:57 AM 02-08-2025",
    "matches": [
        {
            "event_category": "Cricket",
            "title": "Pakistan Champions vs South Africa Champions (World Championship of Legends, 2025)",
            "src": "https://www.fancode.com/skillup-uploads/cms-media/129726_5370_PNC_SAC_fc-Web.jpg",
            "team_1": "Pakistan Champions",
            "team_2": "South Africa Champions",
            "status": "UPCOMING",
            "event_name": "World Championship of Legends, 2025",
            "match_name": "Pakistan Champions vs South Africa Champions",
            "match_id": 129735,
            "startTime": "09:00:00 PM 02-08-2025"
        },
        {
            "event_category": "Cricket",
            "title": "Pahang vs Selangor (MCA Men's T20 Inter-State Championship, 2025)",
            "src": "https://www.fancode.com/skillup-uploads/cms-media/132610_5524_PHG_SEL_fc-web.jpg",
            "team_1": "Pahang",
            "team_2": "Selangor",
            "status": "UPCOMING",
            "event_name": "MCA Men's T20 Inter-State Championship, 2025",
            "match_name": "Pahang vs Selangor",
            "match_id": 132610,
            "startTime": "07:00:00 AM 02-08-2025"
        },
        {
            "event_category": "Cricket",
            "title": "Johor vs Kelantan (MCA Men's T20 Inter-State Championship, 2025)",
            "src": "https://www.fancode.com/skillup-uploads/cms-media/132611_5524_JOH_KEL_fc-web.jpg",
            "team_1": "Johor",
            "team_2": "Kelantan",
            "status": "UPCOMING",
            "event_name": "MCA Men's T20 Inter-State Championship, 2025",
            "match_name": "Johor vs Kelantan",
            "match_id": 132611,
            "startTime": "07:30:00 AM 02-08-2025"
        },
        {
            "event_category": "Cricket",
            "title": "Navarang Club vs Gauhati Town Club (GTC Spring T20 Cup, 2nd Edition, 2025)",
            "src": "https://images.fancode.com/aig/match/v1/132397_CASACARDS_APP.png",
            "team_1": "Navarang Club",
            "team_2": "Gauhati Town Club",
            "status": "UPCOMING",
            "event_name": "GTC Spring T20 Cup, 2nd Edition, 2025",
            "match_name": "Navarang Club vs Gauhati Town Club",
            "match_id": 132397,
            "startTime": "09:00:00 AM 02-08-2025"
        },
        {
            "event_category": "Cricket",
            "title": "Rays vs Magic (Mackay T20 Championship, 2025)",
            "src": "https://www.fancode.com/skillup-uploads/cms-media/132520_5522_RYS_MGC_fc-web.jpg",
            "team_1": "Rays",
            "team_2": "Magic",
            "status": "UPCOMING",
            "event_name": "Mackay T20 Championship, 2025",
            "match_name": "Rays vs Magic",
            "match_id": 132520,
            "startTime": "10:00:00 AM 02-08-2025"
        },
        {
            "event_category": "Cricket",
            "title": "Putrajaya vs Perak (MCA Men's T20 Inter-State Championship, 2025)",
            "src": "https://www.fancode.com/skillup-uploads/cms-media/132612_5524_PJY_PER_fc-web.jpg",
            "team_1": "Putrajaya",
            "team_2": "Perak",
            "status": "UPCOMING",
            "event_name": "MCA Men's T20 Inter-State Championship, 2025",
            "match_name": "Putrajaya vs Perak",
            "match_id": 132612,
            "startTime": "11:30:00 AM 02-08-2025"
        },
        {
            "event_category": "Cricket",
            "title": "Kuala Lumpur vs Sarawak (MCA Men's T20 Inter-State Championship, 2025)",
            "src": "https://www.fancode.com/skillup-uploads/cms-media/132613_5524_KL_SAR_fc-web.jpg",
            "team_1": "Kuala Lumpur",
            "team_2": "Sarawak",
            "status": "UPCOMING",
            "event_name": "MCA Men's T20 Inter-State Championship, 2025",
            "match_name": "Kuala Lumpur vs Sarawak",
            "match_id": 132613,
            "startTime": "12:00:00 PM 02-08-2025"
        },
        {
            "event_category": "Cricket",
            "title": "Sloggers vs Pirates (ECS Gibraltar, 2025)",
            "src": "https://www.fancode.com/skillup-uploads/cms-media/132820_5531_SLO_PIR_fc-web.jpg",
            "team_1": "Sloggers",
            "team_2": "Pirates",
            "status": "UPCOMING",
            "event_name": "ECS Gibraltar, 2025",
            "match_name": "Sloggers vs Pirates",
            "match_id": 132820,
            "startTime": "12:15:00 PM 02-08-2025"
        },
        {
            "event_category": "Cricket",
            "title": "NPL Bears vs Pupkewitz Motors Wildcats (Namibia T20, 2025)",
            "src": "https://www.fancode.com/skillup-uploads/cms-media/Namibia-Domestic-T20_match-card.jpg",
            "team_1": "NPL Bears",
            "team_2": "Pupkewitz Motors Wildcats",
            "status": "UPCOMING",
            "event_name": "Namibia T20, 2025",
            "match_name": "NPL Bears vs Pupkewitz Motors Wildcats",
            "match_id": 132435,
            "startTime": "01:00:00 PM 02-08-2025"
        },
        {
            "event_category": "Cricket",
            "title": "91 Yards Club vs Guwahati Giants (GTC Spring T20 Cup, 2nd Edition, 2025)",
            "src": "https://images.fancode.com/aig/match/v2/132398_CASACARDS_APP.png",
            "team_1": "91 Yards Club",
            "team_2": "Guwahati Giants",
            "status": "UPCOMING",
            "event_name": "GTC Spring T20 Cup, 2nd Edition, 2025",
            "match_name": "91 Yards Club vs Guwahati Giants",
            "match_id": 132398,
            "startTime": "01:15:00 PM 02-08-2025"
        },
        {
            "event_category": "Cricket",
            "title": "Chargers vs Wolves (Mackay T20 Championship, 2025)",
            "src": "https://www.fancode.com/skillup-uploads/cms-media/132524_5522_CHR_WLV_fc-web.jpg",
            "team_1": "Chargers",
            "team_2": "Wolves",
            "status": "UPCOMING",
            "event_name": "Mackay T20 Championship, 2025",
            "match_name": "Chargers vs Wolves",
            "match_id": 132524,
            "startTime": "01:30:00 PM 02-08-2025"
        },
        {
            "event_category": "Cricket",
            "title": "Gaming CC vs Rugby CC (ECS Gibraltar, 2025)",
            "src": "https://www.fancode.com/skillup-uploads/cms-media/132821_5531_GAM_RGC_fc-web.jpg",
            "team_1": "Gaming CC",
            "team_2": "Rugby CC",
            "status": "UPCOMING",
            "event_name": "ECS Gibraltar, 2025",
            "match_name": "Gaming CC vs Rugby CC",
            "match_id": 132821,
            "startTime": "02:15:00 PM 02-08-2025"
        },
        {
            "event_category": "Cricket",
            "title": "Sloggers vs Gaming CC (ECS Gibraltar, 2025)",
            "src": "https://www.fancode.com/skillup-uploads/cms-media/132822_5531_SLO_GAM_fc-web.jpg",
            "team_1": "Sloggers",
            "team_2": "Gaming CC",
            "status": "UPCOMING",
            "event_name": "ECS Gibraltar, 2025",
            "match_name": "Sloggers vs Gaming CC",
            "match_id": 132822,
            "startTime": "04:15:00 PM 02-08-2025"
        },
        {
            "event_category": "Cricket",
            "title": "Paratus Jets vs Eavion Eagles (Namibia T20, 2025)",
            "src": "https://www.fancode.com/skillup-uploads/cms-media/Namibia-Domestic-T20_match-card.jpg",
            "team_1": "Paratus Jets",
            "team_2": "Eavion Eagles",
            "status": "UPCOMING",
            "event_name": "Namibia T20, 2025",
            "match_name": "Paratus Jets vs Eavion Eagles",
            "match_id": 132436,
            "startTime": "05:30:00 PM 02-08-2025"
        },
        {
            "event_category": "Cricket",
            "title": "Rugby CC vs Pirates (ECS Gibraltar, 2025)",
            "src": "https://www.fancode.com/skillup-uploads/cms-media/132823_5531_RGC_PIR_fc-web.jpg",
            "team_1": "Rugby CC",
            "team_2": "Pirates",
            "status": "UPCOMING",
            "event_name": "ECS Gibraltar, 2025",
            "match_name": "Rugby CC vs Pirates",
            "match_id": 132823,
            "startTime": "06:15:00 PM 02-08-2025"
        },
        {
            "event_category": "Cricket",
            "title": "Sloggers vs Rugby CC (ECS Gibraltar, 2025)",
            "src": "https://www.fancode.com/skillup-uploads/cms-media/132824_5531_SLO_RGC_fc-web.jpg",
            "team_1": "Sloggers",
            "team_2": "Rugby CC",
            "status": "UPCOMING",
            "event_name": "ECS Gibraltar, 2025",
            "match_name": "Sloggers vs Rugby CC",
            "match_id": 132824,
            "startTime": "08:15:00 PM 02-08-2025"
        },
        {
            "event_category": "Cricket",
            "title": "ACE KRM Panthers vs Fakhr-E-Kashmir (KCC T20 Summer League, 2025)",
            "src": "https://www.fancode.com/skillup-uploads/cms-media/KCC-T20-Summer-League_old_01.jpg",
            "team_1": "ACE KRM Panthers",
            "team_2": "Fakhr-E-Kashmir",
            "status": "UPCOMING",
            "event_name": "KCC T20 Summer League, 2025",
            "match_name": "ACE KRM Panthers vs Fakhr-E-Kashmir",
            "match_id": 130017,
            "startTime": "10:30:00 PM 02-08-2025"
        },
        {
            "event_category": "Cricket",
            "title": "Gaming CC vs Pirates (ECS Gibraltar, 2025)",
            "src": "https://www.fancode.com/skillup-uploads/cms-media/132825_5531_GAM_PIR_fc-web.jpg",
            "team_1": "Gaming CC",
            "team_2": "Pirates",
            "status": "UPCOMING",
            "event_name": "ECS Gibraltar, 2025",
            "match_name": "Gaming CC vs Pirates",
            "match_id": 132825,
            "startTime": "10:30:00 PM 02-08-2025"
        },
        {
            "event_category": "Cricket",
            "title": "Sloggers vs Pirates (ECS Gibraltar, 2025)",
            "src": "https://www.fancode.com/skillup-uploads/cms-media/132826_5531_SLO_PIR_fc-web.jpg",
            "team_1": "Sloggers",
            "team_2": "Pirates",
            "status": "UPCOMING",
            "event_name": "ECS Gibraltar, 2025",
            "match_name": "Sloggers vs Pirates",
            "match_id": 132826,
            "startTime": "12:30:00 AM 03-08-2025"
        },
        {
            "event_category": "Football",
            "title": "Barnet vs Fleetwood Town (League Two 2025-26)",
            "src": "https://www.fancode.com/skillup-uploads/cms-media/League-Two-2025-26_match-card.jpg",
            "team_1": "Barnet",
            "team_2": "Fleetwood Town",
            "status": "UPCOMING",
            "event_name": "League Two 2025-26",
            "match_name": "Barnet vs Fleetwood Town",
            "match_id": 132023,
            "startTime": "07:30:00 PM 02-08-2025"
        },
        {
            "event_category": "Football",
            "title": "Bradford City vs Wycombe Wanderers (League One 2025-26)",
            "src": "https://www.fancode.com/skillup-uploads/cms-media/League-One-2025-26_match-card.jpg",
            "team_1": "Bradford City",
            "team_2": "Wycombe Wanderers",
            "status": "UPCOMING",
            "event_name": "League One 2025-26",
            "match_name": "Bradford City vs Wycombe Wanderers",
            "match_id": 132019,
            "startTime": "07:30:00 PM 02-08-2025"
        },
        {
            "event_category": "Football",
            "title": "Cardiff City vs Peterborough United (League One 2025-26)",
            "src": "https://www.fancode.com/skillup-uploads/cms-media/League-One-2025-26_match-card.jpg",
            "team_1": "Cardiff City",
            "team_2": "Peterborough United",
            "status": "UPCOMING",
            "event_name": "League One 2025-26",
            "match_name": "Cardiff City vs Peterborough United",
            "match_id": 132013,
            "startTime": "08:00:00 PM 02-08-2025"
        },
        {
            "event_category": "Cricket",
            "title": "Marlins vs Rockets (Mackay T20 Championship, 2025)",
            "src": "https://www.fancode.com/skillup-uploads/cms-media/132516_5522_MAR_RCS_fc-web.jpg",
            "team_1": "Marlins",
            "team_2": "Rockets",
            "status": "UPCOMING",
            "event_name": "Mackay T20 Championship, 2025",
            "match_name": "Marlins vs Rockets",
            "match_id": 132516,
            "startTime": "04:30:00 AM 03-08-2025"
        },
        {
            "event_category": "Baseball",
            "title": "Seattle Mariners vs Texas Rangers (Major League Baseball, 2025)",
            "src": "https://images.fancode.com/aig/match/v1/132835_CASACARDS_APP.png",
            "team_1": "Seattle Mariners",
            "team_2": "Texas Rangers",
            "status": "UPCOMING",
            "event_name": "Major League Baseball, 2025",
            "match_name": "Seattle Mariners vs Texas Rangers",
            "match_id": 132835,
            "startTime": "07:40:00 AM 02-08-2025"
        },
        {
            "event_category": "Motorsports",
            "title": "Sprint Race vs Budapest (F3 HUNGARY 2025)",
            "src": "https://www.fancode.com/skillup-uploads/cms-media/F3_Old_match-card_2.jpg",
            "team_1": "Sprint Race",
            "team_2": "Budapest",
            "status": "UPCOMING",
            "event_name": "F3 HUNGARY 2025",
            "match_name": "Sprint Race",
            "match_id": 119106,
            "startTime": "01:35:00 PM 02-08-2025"
        },
        {
            "event_category": "Cricket",
            "title": "Melaka vs Pahang (MCA Men's T20 Inter-State Championship, 2025)",
            "src": "https://www.fancode.com/skillup-uploads/cms-media/132614_5524_MEL_PHG_fc-web.jpg",
            "team_1": "Melaka",
            "team_2": "Pahang",
            "status": "UPCOMING",
            "event_name": "MCA Men's T20 Inter-State Championship, 2025",
            "match_name": "Melaka vs Pahang",
            "match_id": 132614,
            "startTime": "07:00:00 AM 03-08-2025"
        },
        {
            "event_category": "Motorsports",
            "title": "Qualifying Session vs Budapest (Porsche Mobil 1 Super Cup)",
            "src": "https://www.fancode.com/skillup-uploads/cms-media/Porsche-Mobil-1-Supercup_Hungarian_GP__Match_card_MRF_Old_match-card.jpg",
            "team_1": "Qualifying Session",
            "team_2": "Budapest",
            "status": "UPCOMING",
            "event_name": "Porsche Mobil 1 Super Cup",
            "match_name": "Qualifying Session",
            "match_id": 132113,
            "startTime": "02:50:00 PM 02-08-2025"
        },
        {
            "event_category": "Formula 1",
            "title": "Practice 3 vs Hungary (F1 LENOVO HUNGARIAN GRAND PRIX 2025)",
            "src": "https://www.fancode.com/skillup-uploads/cms-media/F1_Hungarian-Grand-Prix_old.jpg",
            "team_1": "Practice 3",
            "team_2": "Hungary",
            "status": "UPCOMING",
            "event_name": "F1 LENOVO HUNGARIAN GRAND PRIX 2025",
            "match_name": "Practice 3",
            "match_id": 118448,
            "startTime": "04:00:00 PM 02-08-2025"
        },
        {
            "event_category": "Golf",
            "title": "Main Feed - Day 3 vs Sedgefield Country Club - Greensboro, NC (Wyndham Championship 2025)",
            "src": "https://www.fancode.com/skillup-uploads/cms-media/Wyndham-Championship-old-match-card.png",
            "team_1": "Main Feed - Day 3",
            "team_2": "Sedgefield Country Club - Greensboro, NC",
            "status": "UPCOMING",
            "event_name": "Wyndham Championship 2025",
            "match_name": "Main Feed - Day 3",
            "match_id": 132211,
            "startTime": "05:15:00 PM 02-08-2025"
        },
        {
            "event_category": "Golf",
            "title": "Marquee Group - Day 3 vs Sedgefield Country Club - Greensboro, NC (Wyndham Championship 2025)",
            "src": "https://www.fancode.com/skillup-uploads/cms-media/Wyndham-Championship-old-match-card.png",
            "team_1": "Marquee Group - Day 3",
            "team_2": "Sedgefield Country Club - Greensboro, NC",
            "status": "UPCOMING",
            "event_name": "Wyndham Championship 2025",
            "match_name": "Marquee Group - Day 3",
            "match_id": 132212,
            "startTime": "05:30:00 PM 02-08-2025"
        },
        {
            "event_category": "Motorsports",
            "title": "Sprint Race vs Budapest (F2 HUNGARY 2025)",
            "src": "https://www.fancode.com/skillup-uploads/cms-media/Formula2_Old_match-card-(1).jpg",
            "team_1": "Sprint Race",
            "team_2": "Budapest",
            "status": "UPCOMING",
            "event_name": "F2 HUNGARY 2025",
            "match_name": "Sprint Race",
            "match_id": 119063,
            "startTime": "05:45:00 PM 02-08-2025"
        },
        {
            "event_category": "Golf",
            "title": "Featured Holes - Day 3 vs Sedgefield Country Club - Greensboro, NC (Wyndham Championship 2025)",
            "src": "https://www.fancode.com/skillup-uploads/cms-media/Wyndham-Championship-old-match-card.png",
            "team_1": "Featured Holes - Day 3",
            "team_2": "Sedgefield Country Club - Greensboro, NC",
            "status": "UPCOMING",
            "event_name": "Wyndham Championship 2025",
            "match_name": "Featured Holes - Day 3",
            "match_id": 132214,
            "startTime": "05:45:00 PM 02-08-2025"
        },
        {
            "event_category": "Golf",
            "title": "Featured Group - Day 3 vs Sedgefield Country Club - Greensboro, NC (Wyndham Championship 2025)",
            "src": "https://www.fancode.com/skillup-uploads/cms-media/Wyndham-Championship-old-match-card.png",
            "team_1": "Featured Group - Day 3",
            "team_2": "Sedgefield Country Club - Greensboro, NC",
            "status": "UPCOMING",
            "event_name": "Wyndham Championship 2025",
            "match_name": "Featured Group - Day 3",
            "match_id": 132213,
            "startTime": "06:00:00 PM 02-08-2025"
        },
        {
            "event_category": "Cricket",
            "title": "Selangor vs Kelantan (MCA Men's T20 Inter-State Championship, 2025)",
            "src": "https://www.fancode.com/skillup-uploads/cms-media/132624_5524_SEL_KEL_fc-web.jpg",
            "team_1": "Selangor",
            "team_2": "Kelantan",
            "status": "UPCOMING",
            "event_name": "MCA Men's T20 Inter-State Championship, 2025",
            "match_name": "Selangor vs Kelantan",
            "match_id": 132624,
            "startTime": "07:30:00 AM 03-08-2025"
        },
        {
            "event_category": "Formula 1",
            "title": "Qualifying vs Hungary (F1 LENOVO HUNGARIAN GRAND PRIX 2025)",
            "src": "https://www.fancode.com/skillup-uploads/cms-media/F1_Hungarian-Grand-Prix_old.jpg",
            "team_1": "Qualifying",
            "team_2": "Hungary",
            "status": "UPCOMING",
            "event_name": "F1 LENOVO HUNGARIAN GRAND PRIX 2025",
            "match_name": "Qualifying",
            "match_id": 118449,
            "startTime": "07:30:00 PM 02-08-2025"
        },
        {
            "event_category": "Cricket",
            "title": "South Delhi Superstarz vs East Delhi Riders (Delhi Premier League, 2025)",
            "src": "https://www.fancode.com/skillup-uploads/cms-media/Cricket_Fallback_Old_match-card.jpg",
            "team_1": "South Delhi Superstarz",
            "team_2": "East Delhi Riders",
            "status": "UPCOMING",
            "event_name": "Delhi Premier League, 2025",
            "match_name": "South Delhi Superstarz vs East Delhi Riders",
            "match_id": 132464,
            "startTime": "08:00:00 PM 02-08-2025"
        },
        {
            "event_category": "Cricket",
            "title": "TBC vs TBC (Mackay T20 Championship, 2025)",
            "src": "https://www.fancode.com/skillup-uploads/cms-media/Cricket_Fallback_Old_match-card.jpg",
            "team_1": "TBC",
            "team_2": "TBC",
            "status": "UPCOMING",
            "event_name": "Mackay T20 Championship, 2025",
            "match_name": "TBC vs TBC",
            "match_id": 132525,
            "startTime": "08:00:00 AM 03-08-2025"
        }
    ]
}