{
    "name": "Fancode Live Matches Data in Json",
    "telegram": "https://t.me/+rQTz5VL8CRpjNTZl",
    "last update time": "08:17:26 PM 18-02-2025",
    "matches": [
        {
            "event_category": "Cricket",
            "title": "Ireland vs Zimbabwe (Ireland tour of Zimbabwe, 2025)",
            "src": "https://www.fancode.com/skillup-uploads/cms-media/Ireland-Tour-of-Zimbabwe--ODIs_old.jpg",
            "team_1": "Ireland",
            "team_2": "Zimbabwe",
            "status": "LIVE",
            "event_name": "Ireland tour of Zimbabwe, 2025",
            "match_name": "Ireland vs Zimbabwe",
            "match_id": 116938,
            "startTime": "01:00:00 PM 18-02-2025",
            "dai_url": "https://dai.google.com/linear/hls/event/Dz4WU6dhSlSQ3Or8hR61Sg/master.m3u8",
            "adfree_url": "https://dai.fancode.com/primary/116938_english_hls_5267ta-no/index.m3u8"
        },
        {
            "event_category": "Cricket",
            "title": "Kanoo Strikers vs Bin Dilmah (Saudi Foundation T20 Cup, 2025)",
            "src": "https://www.fancode.com/skillup-uploads/cms-media/118942_4891_BD_KS_fc-web.jpg",
            "team_1": "Kanoo Strikers",
            "team_2": "Bin Dilmah",
            "status": "LIVE",
            "event_name": "Saudi Foundation T20 Cup, 2025",
            "match_name": "Kanoo Strikers vs Bin Dilmah",
            "match_id": 118942,
            "startTime": "06:00:00 PM 18-02-2025",
            "dai_url": "https://dai.google.com/linear/hls/event/KA055kKVQCylHCLQ85s-Dg/master.m3u8",
            "adfree_url": "https://dai.fancode.com/primary/118942_english_hls_5424ta-no/index.m3u8"
        },
        {
            "event_category": "Cricket",
            "title": "Hamrun Stallions vs Swieqi United (ECS Malta, 2025)",
            "src": "https://www.fancode.com/skillup-uploads/cms-media/BOX-Office-White-Ball-T20-old-Match-card.png",
            "team_1": "Hamrun Stallions",
            "team_2": "Swieqi United",
            "status": "LIVE",
            "event_name": "ECS Malta, 2025",
            "match_name": "Hamrun Stallions vs Swieqi United",
            "match_id": 118289,
            "startTime": "06:45:00 PM 18-02-2025",
            "dai_url": "https://dai.google.com/linear/hls/event/lq9fIJZ7Q_SVDSNUEPhKuQ/master.m3u8",
            "adfree_url": "https://dai.fancode.com/primary/118289_english_hls_5538ta-no/index.m3u8"
        },
        {
            "event_category": "Football",
            "title": "Tractor vs Khaldiya (AFC Champions League Two 2024-25)",
            "src": "https://www.fancode.com/skillup-uploads/cms-media/117666_4476_TFC_KHA_fc-Web.jpg",
            "team_1": "Tractor",
            "team_2": "Khaldiya",
            "status": "LIVE",
            "event_name": "AFC Champions League Two 2024-25",
            "match_name": "Tractor vs Khaldiya",
            "match_id": 117666,
            "startTime": "07:30:00 PM 18-02-2025",
            "dai_url": "https://dai.google.com/linear/hls/event/VbJLfDfBTwyDjjDjwrNlJw/master.m3u8",
            "adfree_url": "https://dai.fancode.com/primary/117666_english_hls_5657ta-di/index.m3u8"
        },
        {
            "event_category": "Football",
            "title": "Sharjah vs Al Hussein (AFC Champions League Two 2024-25)",
            "src": "https://www.fancode.com/skillup-uploads/cms-media/117667_4476_SHJ_HUS_fc-Web.jpg",
            "team_1": "Sharjah",
            "team_2": "Al Hussein",
            "status": "LIVE",
            "event_name": "AFC Champions League Two 2024-25",
            "match_name": "Sharjah vs Al Hussein",
            "match_id": 117667,
            "startTime": "07:30:00 PM 18-02-2025",
            "dai_url": "https://dai.google.com/linear/hls/event/1EfeCFQ8QX-uWFfMzDhotw/master.m3u8",
            "adfree_url": "https://dai.fancode.com/primary/117667_english_hls_5296ta-di/index.m3u8"
        },
        {
            "event_category": "Cricket",
            "title": "New South Wales vs Victoria (Sheffield Shield, 2024-25)",
            "src": "https://www.fancode.com/skillup-uploads/cms-media/110412_4543_NSW_VCT_fc-Web_1739782530659.jpg",
            "team_1": "New South Wales",
            "team_2": "Victoria",
            "status": "PAUSED",
            "event_name": "Sheffield Shield, 2024-25",
            "match_name": "New South Wales vs Victoria",
            "match_id": 110412,
            "startTime": "05:00:00 AM 18-02-2025"
        },
        {
            "event_category": "Cricket",
            "title": "Queensland vs Western Australia (Sheffield Shield, 2024-25)",
            "src": "https://www.fancode.com/skillup-uploads/cms-media/110413_4543_QUN_WAU_fc-Web_1739782530557.jpg",
            "team_1": "Queensland",
            "team_2": "Western Australia",
            "status": "PAUSED",
            "event_name": "Sheffield Shield, 2024-25",
            "match_name": "Queensland vs Western Australia",
            "match_id": 110413,
            "startTime": "05:30:00 AM 18-02-2025"
        },
        {
            "event_category": "Cricket",
            "title": "South Australia vs Tasmania (Sheffield Shield, 2024-25)",
            "src": "https://www.fancode.com/skillup-uploads/cms-media/110419_4543_SAU_TAS_fc-Web_1739782530681.jpg",
            "team_1": "South Australia",
            "team_2": "Tasmania",
            "status": "PAUSED",
            "event_name": "Sheffield Shield, 2024-25",
            "match_name": "South Australia vs Tasmania",
            "match_id": 110419,
            "startTime": "05:30:00 AM 18-02-2025"
        },
        {
            "event_category": "Cricket",
            "title": "Cloud 7 vs Tafga CC (Saudi Foundation T20 Cup, 2025)",
            "src": "https://www.fancode.com/skillup-uploads/cms-media/118943_4891_CLO_TAG_fc-web.jpg",
            "team_1": "Cloud 7",
            "team_2": "Tafga CC",
            "status": "UPCOMING",
            "event_name": "Saudi Foundation T20 Cup, 2025",
            "match_name": "Cloud 7 vs Tafga CC",
            "match_id": 118943,
            "startTime": "10:30:00 PM 18-02-2025"
        },
        {
            "event_category": "Cricket",
            "title": "MEC Study Group vs GAT (KCC T20 Challengers A League, 2025)",
            "src": "https://www.fancode.com/skillup-uploads/cms-media/KCC-T20-Challengers-A_league_match-card_1739168693257.jpg",
            "team_1": "MEC Study Group",
            "team_2": "GAT",
            "status": "UPCOMING",
            "event_name": "KCC T20 Challengers A League, 2025",
            "match_name": "MEC Study Group vs GAT",
            "match_id": 118079,
            "startTime": "11:00:00 PM 18-02-2025"
        },
        {
            "event_category": "Cricket",
            "title": "Lisbon Capitals vs Malo (ECSN Portugal, 2025)",
            "src": "https://www.fancode.com/skillup-uploads/cms-media/117786_4800_LCA_MAL_fc-web.jpg",
            "team_1": "Lisbon Capitals",
            "team_2": "Malo",
            "status": "UPCOMING",
            "event_name": "ECSN Portugal, 2025",
            "match_name": "Lisbon Capitals vs Malo",
            "match_id": 117787,
            "startTime": "11:30:00 PM 18-02-2025"
        },
        {
            "event_category": "Cricket",
            "title": "Punjab CC Amadora vs TBC (ECSN Portugal, 2025)",
            "src": "https://www.fancode.com/skillup-uploads/cms-media/Cricket_Fallback_Old_match-card.jpg",
            "team_1": "Punjab CC Amadora",
            "team_2": "TBC",
            "status": "UPCOMING",
            "event_name": "ECSN Portugal, 2025",
            "match_name": "Punjab CC Amadora vs TBC",
            "match_id": 117788,
            "startTime": "02:30:00 AM 19-02-2025"
        }
    ]
}